{
  "executionTaskId": 5,
  "runNo": 3,
  "summaryText": "仓库扫描完成，共发现 886 个问题。",
  "artifacts": [
    {
      "artifactType": "SCAN_MANIFEST",
      "fileName": "scan-manifest.json"
    },
    {
      "artifactType": "SEMGREP_JSON",
      "fileName": "semgrep.json"
    },
    {
      "artifactType": "SEMGREP_SARIF",
      "fileName": "semgrep.sarif"
    },
    {
      "artifactType": "FINDING_INDEX_JSON",
      "fileName": "finding-index.json"
    },
    {
      "artifactType": "REPORT_MARKDOWN",
      "fileName": "report.md"
    },
    {
      "artifactType": "REPORT_HTML",
      "fileName": "report.html"
    },
    {
      "artifactType": "SCAN_LOG",
      "fileName": "scan.log"
    }
  ]
}